aime_text_postprocessing/__init__.py
aime_text_postprocessing/dictionary_db.py
aime_text_postprocessing/kanjikana.py
aime_text_postprocessing/text_replace.py
aime_text_postprocessing-0.0.5.post1.dist-info/LICENSE.txt
aime_text_postprocessing-0.0.5.post1.dist-info/METADATA
aime_text_postprocessing-0.0.5.post1.dist-info/WHEEL
aime_text_postprocessing-0.0.5.post1.dist-info/top_level.txt
aime_text_postprocessing-0.0.5.post1.dist-info/RECORD
