Metadata-Version: 2.1
Name: aime-text-postprocessing
Version: 0.0.5.post1
Summary: Base module for human detection
Home-page: https://github.com/jarklee/aime_text_postprocessing
Author: TrinhQuan
Author-email: quantv@aimesoft.com
License: UNKNOWN
Download-URL: https://github.com/jarklee/aime_text_postprocessing/releases/download/0.0.5/aime_text_postprocessing-0.0.5-post1.tar.gz
Platform: UNKNOWN
Classifier: Programming Language :: Python :: 3.6
Classifier: Programming Language :: Python :: 3.7
Classifier: License :: OSI Approved :: MIT License
Requires-Dist: win-unicode-console (==0.5)
Requires-Dist: romkan (==0.2.1)
Requires-Dist: chardet (==3.0.4)
